openECCI/__init__.py
openECCI/ctf.py
openECCI/io.py
openECCI/optimization.py
openECCI/release.py
openECCI/rkp.py
openECCI/stagecomputation.py
openECCI/util.py
openECCI-0.1.0.dist-info/LICENSE.txt
openECCI-0.1.0.dist-info/METADATA
openECCI-0.1.0.dist-info/WHEEL
openECCI-0.1.0.dist-info/top_level.txt
openECCI-0.1.0.dist-info/zip-safe
openECCI-0.1.0.dist-info/RECORD
